{"EHPAD":[{"name":"ehpad du centre hospitalier de doué la fontaine","street":"30 ter, rue Saint-François","cp":"BP 39","phone":"02 41 83 46 10","pricing":[{"singleRoom":"61,95€","doubleRoom":"61,95€"},{"singleRoom":"61,95€","doubleRoom":"61,95€"}],"categories":"EHPAD | Accueil de jour | Hébergement temporaire | Hébergement permanent | PASA | Conventionné APL | Habilité ASH"},{"name":"ehpad euphrasie-pelletier","street":"9, rue Brault","cp":"49000 ANGERS","phone":"02 41 19 01 01","pricing":[{"singleRoom":"62,30€","doubleRoom":"62,30€"}],"categories":"EHPAD | Hébergement permanent | Unité Alzheimer | Conventionné APL | Habilité ASH"},{"name":"ehpad notre-dame du bon secours","street":"1, rue Notre-Dame-du-Bon-Secours","cp":"49110 LE PIN EN MAUGES","phone":"02 41 70 00 19","pricing":[{"singleRoom":"62,31€","doubleRoom":"62,31€"}],"categories":"EHPAD | Accueil de jour | Hébergement temporaire | Hébergement permanent | Unité Alzheimer | Conventionné APL | Habilité ASH"},{"name":"ehpad hôpital de la corniche angevine","street":"1, rue Saint-Jean","cp":"49190 ROCHEFORT SUR LOIRE","phone":"02 41 74 27 40","pricing":[{"singleRoom":"62,34€","doubleRoom":"62,34€"},{"singleRoom":"60,00€","doubleRoom":"60,00€"}],"categories":"EHPAD | Hébergement permanent | Habilité ASH"},{"name":"ehpad hôpital de la corniche angevine","street":"13, avenue Jean-Robin","cp":"49290 CHALONNES SUR LOIRE","phone":"02 41 74 27 40","pricing":[{"singleRoom":"62,34€","doubleRoom":"62,34€"},{"singleRoom":"60,00€","doubleRoom":"60,00€"}],"categories":"EHPAD | Hébergement permanent | Unité Alzheimer | Habilité ASH"},{"name":"ehpad les troènes","street":"2, rue du Centre","cp":"BP 51506","phone":"02 41 75 72 01","pricing":[{"singleRoom":"62,35€","doubleRoom":"62,35€"}],"categories":"EHPAD | Hébergement permanent | Conventionné APL | Habilité ASH"},{"name":"ehpad - site de mazé","street":"15, rue Paul-Richou","cp":"49630 MAZE","phone":"02 41 80 60 27","pricing":[{"singleRoom":"62,66€","doubleRoom":"62,66€"},{"singleRoom":"62,12€","doubleRoom":"62,12€"}],"categories":"EHPAD | Hébergement permanent | Habilité ASH"},{"name":"ehpad esbv - site de ménitré","street":"1, rue Joliot Curie","cp":"49250 LA MENITRE","phone":"02 41 45 67 67","pricing":[{"singleRoom":"62,66€","doubleRoom":"62,66€"},{"singleRoom":"62,12€","doubleRoom":"62,12€"}],"categories":"EHPAD | Hébergement temporaire | Hébergement permanent | Habilité ASH"},{"name":"ehpad - site de baugé","street":"9, chemin de Rancan","cp":"49150 BAUGE EN ANJOU","phone":"02 41 84 13 84","pricing":[{"singleRoom":"62,66€","doubleRoom":"62,66€"},{"singleRoom":"62,12€","doubleRoom":"62,12€"}],"categories":"EHPAD | Hébergement permanent | Unité Alzheimer | Habilité ASH"},{"name":"ehpad esbv","street":"14, rue de l'Hôpital","cp":"BP 89","phone":"02 41 57 50 00","pricing":[{"singleRoom":"62,66€","doubleRoom":"62,66€"},{"singleRoom":"62,12€","doubleRoom":"62,12€"}],"categories":"EHPAD | Hébergement permanent | PASA | Habilité ASH"}]}